{
	"index":"index.html",
	"appData":{
		"test": true
	},
	"assetGroups":[{
		"name":"appshell",
		"resources":{
			"files":[
				"/assets/**/*",
				"!/ngsw-worker.js"
			],
			"versionedFiles":[
				"/**/*.html",
				"/**/*.js",
				"/**/*.css"
			],
			"urls":[
				"https://fonts.googleapis.com/css?family=Material+Icons",
				"https://fonts.googleapis.com/css?family=Material+Icons"
			]
		}
	}],
	"dataGroups":[{
		"name":"api-freshness",
		"urls":[
			"/timeline"
		],
		"cacheConfig":{
			"maxAge":100,
			"maxSize":"3d",
			"timeout":"1m",
			"strategy":"freshness"
		}
	},
	{
		"name":"api-performance",
		"urls":[
			"/favorites"
		],
		"cacheConfig":{
			"maxAge":100,
			"maxSize":"3d",
			"timeout":"1m",
			"strategy":"api-performance"
		}
	}]
}